{
  "day": [
    {
      "0": {
        "numberAttack": 2,
        "time": "2017-03-10T00:00:00.000+0000",
        "trojanFamily": "AndroidBauts"
      },
      "1": {
        "numberAttack": 15,
        "time": "2017-03-11T00:00:00.000+0000",
        "trojanFamily": "Ganlet"
      },
      "2": {
        "numberAttack": 1,
        "time": "2017-03-12T00:00:00.000+0000",
        "trojanFamily": "MKero"
      },
      "3": {
        "numberAttack": 8,
        "time": "2017-03-13T00:00:00.000+0000",
        "trojanFamily": "MobiDash"
      },
      "4": {
        "numberAttack": 6,
        "time": "2017-03-14T00:00:00.000+0000",
        "trojanFamily": "Necurs"
      },
      "5": {
        "numberAttack": 3,
        "time": "2017-03-15T00:00:00.000+0000",
        "trojanFamily": "PushDo"
      },
      "6": {
        "numberAttack": 3,
        "time": "2017-03-16T00:00:00.000+0000",
        "trojanFamily": "Ramnit"
      },
      "7": {
        "numberAttack": 4,
        "time": "2017-03-17T00:00:00.000+0000",
        "trojanFamily": "Ztorg"
      },
      "8": {
        "numberAttack": 9,
        "time": "2017-03-18T00:00:00.000+0000",
        "trojanFamily": "Test1"
      },
      "9": {
        "numberAttack": 41,
        "time": "2017-03-19T00:00:00.000+0000",
        "trojanFamily": "Test2"
      },
      "10": {
        "numberAttack": 11,
        "time": "2017-03-20T00:00:00.000+0000",
        "trojanFamily": "Test3"
      },
      "11": {
        "numberAttack": 6,
        "time": "2017-03-21T00:00:00.000+0000",
        "trojanFamily": "Test4"
      },
      "12": {
        "numberAttack": 22,
        "time": "2017-03-22T00:00:00.000+0000",
        "trojanFamily": "Test5"
      },
      "13": {
        "numberAttack": 29,
        "time": "2017-03-23T00:00:00.000+0000",
        "trojanFamily": "Test6"
      },
      "14": {
        "numberAttack": 2,
        "time": "2017-03-24T00:00:00.000+0000",
        "trojanFamily": "Test7"
      },
      "15": {
        "numberAttack": 8,
        "time": "2017-03-25T00:00:00.000+0000",
        "trojanFamily": "Test8"
      },
      "16": {
        "numberAttack": 16,
        "time": "2017-03-26T00:00:00.000+0000",
        "trojanFamily": "Test9"
      },
      "17": {
        "numberAttack": 24,
        "time": "2017-03-27T00:00:00.000+0000",
        "trojanFamily": "Test10"
      },
      "18": {
        "numberAttack": 13,
        "time": "2017-03-28T00:00:00.000+0000",
        "trojanFamily": "Test11"
      },
      "count": 181,
      "companyIP": "89.108.195.20",
      "id": 1
    }
  ],
  "hour": [
    {
      "0": {
        "numberAttack": 11,
        "time": "2017-01-10T00:00:00.000+0000",
        "trojanFamily": "AndroidBauts"
      },
      "1": {
        "numberAttack": 33,
        "time": "2017-01-11T00:00:00.000+0000",
        "trojanFamily": "Ganlet"
      },
      "2": {
        "numberAttack": 44,
        "time": "2017-01-12T00:00:00.000+0000",
        "trojanFamily": "MKero"
      },
      "3": {
        "numberAttack": 13,
        "time": "2017-01-13T00:00:00.000+0000",
        "trojanFamily": "MobiDash"
      },
      "4": {
        "numberAttack": 18,
        "time": "2017-01-14T00:00:00.000+0000",
        "trojanFamily": "Necurs"
      },
      "5": {
        "numberAttack": 22,
        "time": "2017-01-15T00:00:00.000+0000",
        "trojanFamily": "PushDo"
      },
      "6": {
        "numberAttack": 9,
        "time": "2017-01-16T00:00:00.000+0000",
        "trojanFamily": "Ramnit"
      },
      "7": {
        "numberAttack": 6,
        "time": "2017-01-17T00:00:00.000+0000",
        "trojanFamily": "Ztorg"
      },
      "8": {
        "numberAttack": 28,
        "time": "2017-01-18T00:00:00.000+0000",
        "trojanFamily": "Test1"
      },
      "9": {
        "numberAttack": 11,
        "time": "2017-01-19T00:00:00.000+0000",
        "trojanFamily": "Test2"
      },
      "10": {
        "numberAttack": 41,
        "time": "2017-01-20T00:00:00.000+0000",
        "trojanFamily": "Test3"
      },
      "11": {
        "numberAttack": 22,
        "time": "2017-01-21T00:00:00.000+0000",
        "trojanFamily": "Test4"
      },
      "12": {
        "numberAttack": 24,
        "time": "2017-01-22T00:00:00.000+0000",
        "trojanFamily": "Test5"
      },
      "13": {
        "numberAttack": 29,
        "time": "2017-01-23T00:00:00.000+0000",
        "trojanFamily": "Test6"
      },
      "14": {
        "numberAttack": 25,
        "time": "2017-01-24T00:00:00.000+0000",
        "trojanFamily": "Test7"
      },
      "15": {
        "numberAttack": 18,
        "time": "2017-01-25T00:00:00.000+0000",
        "trojanFamily": "Test8"
      },
      "16": {
        "numberAttack": 46,
        "time": "2017-01-26T00:00:00.000+0000",
        "trojanFamily": "Test9"
      },
      "17": {
        "numberAttack": 22,
        "time": "2017-01-27T00:00:00.000+0000",
        "trojanFamily": "Test10"
      },
      "18": {
        "numberAttack": 1,
        "time": "2017-01-28T00:00:00.000+0000",
        "trojanFamily": "Test11"
      },
      "count": 181,
      "companyIP": "89.108.195.20",
      "id": 1
    }
  ],
  "week": [
    {
      "0": {
        "numberAttack": 31,
        "time": "2017-11-10T00:00:00.000+0000",
        "trojanFamily": "AndroidBauts"
      },
      "1": {
        "numberAttack": 14,
        "time": "2017-11-11T00:00:00.000+0000",
        "trojanFamily": "Ganlet"
      },
      "2": {
        "numberAttack": 22,
        "time": "2017-11-12T00:00:00.000+0000",
        "trojanFamily": "MKero"
      },
      "3": {
        "numberAttack": 25,
        "time": "2017-11-13T00:00:00.000+0000",
        "trojanFamily": "MobiDash"
      },
      "4": {
        "numberAttack": 15,
        "time": "2017-11-14T00:00:00.000+0000",
        "trojanFamily": "Necurs"
      },
      "5": {
        "numberAttack": 41,
        "time": "2017-11-15T00:00:00.000+0000",
        "trojanFamily": "PushDo"
      },
      "6": {
        "numberAttack": 21,
        "time": "2017-11-16T00:00:00.000+0000",
        "trojanFamily": "Ramnit"
      },
      "7": {
        "numberAttack": 35,
        "time": "2017-11-17T00:00:00.000+0000",
        "trojanFamily": "Ztorg"
      },
      "8": {
        "numberAttack": 40,
        "time": "2017-11-18T00:00:00.000+0000",
        "trojanFamily": "Test1"
      },
      "9": {
        "numberAttack": 12,
        "time": "2017-11-19T00:00:00.000+0000",
        "trojanFamily": "Test2"
      },
      "10": {
        "numberAttack": 25,
        "time": "2017-11-20T00:00:00.000+0000",
        "trojanFamily": "Test3"
      },
      "11": {
        "numberAttack": 43,
        "time": "2017-11-21T00:00:00.000+0000",
        "trojanFamily": "Test4"
      },
      "12": {
        "numberAttack": 29,
        "time": "2017-11-22T00:00:00.000+0000",
        "trojanFamily": "Test5"
      },
      "13": {
        "numberAttack": 8,
        "time": "2017-11-23T00:00:00.000+0000",
        "trojanFamily": "Test6"
      },
      "14": {
        "numberAttack": 35,
        "time": "2017-11-24T00:00:00.000+0000",
        "trojanFamily": "Test7"
      },
      "15": {
        "numberAttack": 18,
        "time": "2017-11-25T00:00:00.000+0000",
        "trojanFamily": "Test8"
      },
      "16": {
        "numberAttack": 12,
        "time": "2017-11-26T00:00:00.000+0000",
        "trojanFamily": "Test9"
      },
      "17": {
        "numberAttack": 29,
        "time": "2017-11-27T00:00:00.000+0000",
        "trojanFamily": "Test10"
      },
      "18": {
        "numberAttack": 16,
        "time": "2017-11-28T00:00:00.000+0000",
        "trojanFamily": "Test11"
      },
      "count": 181,
      "companyIP": "89.108.195.20",
      "id": 1
    }
  ],
  "month": [
    {
      "0": {
        "numberAttack": 11,
        "time": "2017-12-10T00:00:00.000+0000",
        "trojanFamily": "AndroidBauts"
      },
      "1": {
        "numberAttack": 22,
        "time": "2017-12-11T00:00:00.000+0000",
        "trojanFamily": "Ganlet"
      },
      "2": {
        "numberAttack": 33,
        "time": "2017-12-12T00:00:00.000+0000",
        "trojanFamily": "MKero"
      },
      "3": {
        "numberAttack": 12,
        "time": "2017-12-13T00:00:00.000+0000",
        "trojanFamily": "MobiDash"
      },
      "4": {
        "numberAttack": 15,
        "time": "2017-12-14T00:00:00.000+0000",
        "trojanFamily": "Necurs"
      },
      "5": {
        "numberAttack": 12,
        "time": "2017-12-15T00:00:00.000+0000",
        "trojanFamily": "PushDo"
      },
      "6": {
        "numberAttack": 41,
        "time": "2017-12-16T00:00:00.000+0000",
        "trojanFamily": "Ramnit"
      },
      "7": {
        "numberAttack": 16,
        "time": "2017-12-17T00:00:00.000+0000",
        "trojanFamily": "Ztorg"
      },
      "8": {
        "numberAttack": 28,
        "time": "2017-12-18T00:00:00.000+0000",
        "trojanFamily": "Test1"
      },
      "9": {
        "numberAttack": 41,
        "time": "2017-12-19T00:00:00.000+0000",
        "trojanFamily": "Test2"
      },
      "10": {
        "numberAttack": 12,
        "time": "2017-12-20T00:00:00.000+0000",
        "trojanFamily": "Test3"
      },
      "11": {
        "numberAttack": 6,
        "time": "2017-12-21T00:00:00.000+0000",
        "trojanFamily": "Test4"
      },
      "12": {
        "numberAttack": 9,
        "time": "2017-12-22T00:00:00.000+0000",
        "trojanFamily": "Test5"
      },
      "13": {
        "numberAttack": 23,
        "time": "2017-12-23T00:00:00.000+0000",
        "trojanFamily": "Test6"
      },
      "14": {
        "numberAttack": 11,
        "time": "2017-12-24T00:00:00.000+0000",
        "trojanFamily": "Test7"
      },
      "15": {
        "numberAttack": 32,
        "time": "2017-12-25T00:00:00.000+0000",
        "trojanFamily": "Test8"
      },
      "16": {
        "numberAttack": 27,
        "time": "2017-12-26T00:00:00.000+0000",
        "trojanFamily": "Test9"
      },
      "17": {
        "numberAttack": 42,
        "time": "2017-12-27T00:00:00.000+0000",
        "trojanFamily": "Test10"
      },
      "18": {
        "numberAttack": 9,
        "time": "2017-12-28T00:00:00.000+0000",
        "trojanFamily": "Test11"
      },
      "count": 181,
      "companyIP": "89.108.195.20",
      "id": 1
    }
  ],
  "year": [
    {
      "0": {
        "numberAttack": 37,
        "time": "2017-05-10T00:00:00.000+0000",
        "trojanFamily": "AndroidBauts"
      },
      "1": {
        "numberAttack": 23,
        "time": "2017-05-11T00:00:00.000+0000",
        "trojanFamily": "Ganlet"
      },
      "2": {
        "numberAttack": 11,
        "time": "2017-05-12T00:00:00.000+0000",
        "trojanFamily": "MKero"
      },
      "3": {
        "numberAttack": 23,
        "time": "2017-05-13T00:00:00.000+0000",
        "trojanFamily": "MobiDash"
      },
      "4": {
        "numberAttack": 51,
        "time": "2017-05-14T00:00:00.000+0000",
        "trojanFamily": "Necurs"
      },
      "5": {
        "numberAttack": 32,
        "time": "2017-05-15T00:00:00.000+0000",
        "trojanFamily": "PushDo"
      },
      "6": {
        "numberAttack": 23,
        "time": "2017-05-16T00:00:00.000+0000",
        "trojanFamily": "Ramnit"
      },
      "7": {
        "numberAttack": 14,
        "time": "2017-05-17T00:00:00.000+0000",
        "trojanFamily": "Ztorg"
      },
      "8": {
        "numberAttack": 22,
        "time": "2017-05-18T00:00:00.000+0000",
        "trojanFamily": "Test1"
      },
      "9": {
        "numberAttack": 34,
        "time": "2017-05-19T00:00:00.000+0000",
        "trojanFamily": "Test2"
      },
      "10": {
        "numberAttack": 5,
        "time": "2017-05-20T00:00:00.000+0000",
        "trojanFamily": "Test3"
      },
      "11": {
        "numberAttack": 16,
        "time": "2017-05-21T00:00:00.000+0000",
        "trojanFamily": "Test4"
      },
      "12": {
        "numberAttack": 29,
        "time": "2017-05-22T00:00:00.000+0000",
        "trojanFamily": "Test5"
      },
      "13": {
        "numberAttack": 19,
        "time": "2017-05-23T00:00:00.000+0000",
        "trojanFamily": "Test6"
      },
      "14": {
        "numberAttack": 24,
        "time": "2017-05-24T00:00:00.000+0000",
        "trojanFamily": "Test7"
      },
      "15": {
        "numberAttack": 23,
        "time": "2017-05-25T00:00:00.000+0000",
        "trojanFamily": "Test8"
      },
      "16": {
        "numberAttack": 12,
        "time": "2017-05-26T00:00:00.000+0000",
        "trojanFamily": "Test9"
      },
      "17": {
        "numberAttack": 23,
        "time": "2017-05-27T00:00:00.000+0000",
        "trojanFamily": "Test10"
      },
      "18": {
        "numberAttack": 37,
        "time": "2017-05-28T00:00:00.000+0000",
        "trojanFamily": "Test11"
      },
      "count": 181,
      "companyIP": "89.108.195.20",
      "id": 1
    }
  ]
}
